smlmlp/__init__.py
smlmlp/modules/__init__.py
smlmlp/py.typed
smlmlp/routines/__init__.py
smlmlp-0.1.10.dist-info/WHEEL
smlmlp-0.1.10.dist-info/METADATA
smlmlp-0.1.10.dist-info/RECORD
