Metadata-Version: 2.3
Name: smlmlp
Version: 0.1.10
Summary: A python library for Single Molecule Localization Microscopy.
Requires-Dist: corelp
Requires-Python: >=3.12
